geneutil/__init__.py
geneutil/binom.py
geneutil/connect.py
geneutil/fet.py
geneutil/gsea.py
geneutil/ssgsea.py
geneutil/_utils/__init__.py
geneutil/_utils/converter.py
geneutil/dwh/__init__.py
geneutil/dwh/dwh_control.py
geneutil/dwh/dictionary/__init__.py
geneutil/dwh/dictionary/biomart.py
geneutil/dwh/dictionary/biomart/mart_export_HGNC.txt
geneutil/dwh/dictionary/biomart/mart_export_MGI.txt
geneutil/dwh/dictionary/biomart/mart_export_RGD.txt
geneutil/dwh/reference/__init__.py
geneutil/dwh/reference/enrichr.py
geneutil/dwh/reference/msigdb.py
geneutil/dwh/reference/enrichr/human/ChEA_2016.txt
geneutil/dwh/reference/enrichr/human/ENCODE_TF_ChIP-seq_2015.txt
geneutil/dwh/reference/enrichr/human/GO_Biological_Process_2018.txt
geneutil/dwh/reference/enrichr/human/GO_Cellular_Component_2018.txt
geneutil/dwh/reference/enrichr/human/GO_Molecular_Function_2018.txt
geneutil/dwh/reference/enrichr/human/Human_Gene_Atlas.txt
geneutil/dwh/reference/enrichr/human/KEGG_2019_Human.txt
geneutil/dwh/reference/enrichr/human/PPI_Hub_Proteins.txt
geneutil/dwh/reference/enrichr/human/TRANSFAC_and_JASPAR_PWMs.txt
geneutil/dwh/reference/enrichr/mouse/KEGG_2019_Mouse.txt
geneutil/dwh/reference/enrichr/mouse/Mouse_Gene_Atlas.txt
geneutil/dwh/reference/msigdb/c1.all.v7.1.entrez.gmt
geneutil/dwh/reference/msigdb/c2.all.v7.1.entrez.gmt
geneutil/dwh/reference/msigdb/c3.all.v7.1.entrez.gmt
geneutil/dwh/reference/msigdb/c4.all.v7.1.entrez.gmt
geneutil/dwh/reference/msigdb/c5.all.v7.1.entrez.gmt
geneutil/dwh/reference/msigdb/c6.all.v7.1.entrez.gmt
geneutil/dwh/reference/msigdb/c7.all.v7.1.entrez.gmt
geneutil/dwh/reference/msigdb/h.all.v7.1.entrez.gmt
geneutil/enan/__init__.py
geneutil/enan/analyzer.py
geneutil/enan/binom.py
geneutil/enan/connect.py
geneutil/enan/fet.py
geneutil/enan/gsea.py
geneutil/enan/ssgsea.py
geneutil/enan/calculator/__init__.py
geneutil/enan/calculator/_binom.py
geneutil/enan/calculator/_connectivity.py
geneutil/enan/calculator/_fet.py
geneutil/enan/calculator/_gsea.py
geneutil-0.0.11.dist-info/LICENSE.txt
geneutil-0.0.11.dist-info/METADATA
geneutil-0.0.11.dist-info/WHEEL
geneutil-0.0.11.dist-info/top_level.txt
geneutil-0.0.11.dist-info/RECORD
